oauth2_client/__init__.py
oauth2_client/credentials_manager.py
oauth2_client/http_server.py
sd_oauth2_client-1.4.2.dist-info/LICENSE
sd_oauth2_client-1.4.2.dist-info/METADATA
sd_oauth2_client-1.4.2.dist-info/WHEEL
sd_oauth2_client-1.4.2.dist-info/top_level.txt
sd_oauth2_client-1.4.2.dist-info/RECORD
