Metadata-Version: 2.1
Name: sd-oauth2-client
Version: 1.4.2
Summary: A client library for OAuth2
Home-page: http://github.com/securedimensions/OAuth2Client
Author: Andreas Matheus
Author-email: am@secure-dimensions.de
Classifier: Programming Language :: Python
Classifier: Natural Language :: English
Classifier: Operating System :: OS Independent
Classifier: Programming Language :: Python :: 3
Classifier: Programming Language :: Python :: 3.7
Classifier: Programming Language :: Python :: 3.8
Classifier: Programming Language :: Python :: 3.9
Classifier: Programming Language :: Python :: 3.10
Classifier: Programming Language :: Python :: 3.11
Classifier: Topic :: Communications
License-File: LICENSE
Requires-Dist: requests >=2.5.0
